[
  {
    "ContainingType": "ProductCatalog.WebAPI.Controllers.CategoriesController",
    "Method": "GetAllCategoriesAsync",
    "RelativePath": "api/categories",
    "HttpMethod": "GET",
    "IsController": true,
    "Order": 0,
    "Parameters": [],
    "ReturnTypes": []
  },
  {
    "ContainingType": "ProductCatalog.WebAPI.Controllers.CategoriesController",
    "Method": "CreateCategoryAsync",
    "RelativePath": "api/categories",
    "HttpMethod": "POST",
    "IsController": true,
    "Order": 0,
    "Parameters": [
      {
        "Name": "categoryDto",
        "Type": "ProductCatalog.WebAPI.DTOs.Category.CreateCategoryDto",
        "IsRequired": true
      }
    ],
    "ReturnTypes": []
  },
  {
    "ContainingType": "ProductCatalog.WebAPI.Controllers.CategoriesController",
    "Method": "GetCategoryByIdAsync",
    "RelativePath": "api/categories/{id}",
    "HttpMethod": "GET",
    "IsController": true,
    "Order": 0,
    "Parameters": [
      {
        "Name": "id",
        "Type": "System.Int32",
        "IsRequired": true
      }
    ],
    "ReturnTypes": []
  },
  {
    "ContainingType": "ProductCatalog.WebAPI.Controllers.CategoriesController",
    "Method": "UpdateCategoryAsync",
    "RelativePath": "api/categories/{id}",
    "HttpMethod": "PUT",
    "IsController": true,
    "Order": 0,
    "Parameters": [
      {
        "Name": "id",
        "Type": "System.Int32",
        "IsRequired": true
      },
      {
        "Name": "updateCategoryDto",
        "Type": "ProductCatalog.WebAPI.DTOs.Category.UpdateCategoryDto",
        "IsRequired": true
      }
    ],
    "ReturnTypes": []
  },
  {
    "ContainingType": "ProductCatalog.WebAPI.Controllers.CategoriesController",
    "Method": "DeleteCategoryAsync",
    "RelativePath": "api/categories/{id}",
    "HttpMethod": "DELETE",
    "IsController": true,
    "Order": 0,
    "Parameters": [
      {
        "Name": "id",
        "Type": "System.Int32",
        "IsRequired": true
      }
    ],
    "ReturnTypes": []
  },
  {
    "ContainingType": "ProductCatalog.WebAPI.Controllers.ProductsController",
    "Method": "GetAllProductsAsync",
    "RelativePath": "api/products",
    "HttpMethod": "GET",
    "IsController": true,
    "Order": 0,
    "Parameters": [
      {
        "Name": "categoryId",
        "Type": "System.Nullable\u00601[[System.Int32, System.Private.CoreLib, Version=10.0.0.0, Culture=neutral, PublicKeyToken=7cec85d7bea7798e]]",
        "IsRequired": false
      },
      {
        "Name": "minPrice",
        "Type": "System.Nullable\u00601[[System.Decimal, System.Private.CoreLib, Version=10.0.0.0, Culture=neutral, PublicKeyToken=7cec85d7bea7798e]]",
        "IsRequired": false
      },
      {
        "Name": "maxPrice",
        "Type": "System.Nullable\u00601[[System.Decimal, System.Private.CoreLib, Version=10.0.0.0, Culture=neutral, PublicKeyToken=7cec85d7bea7798e]]",
        "IsRequired": false
      },
      {
        "Name": "isActive",
        "Type": "System.Nullable\u00601[[System.Boolean, System.Private.CoreLib, Version=10.0.0.0, Culture=neutral, PublicKeyToken=7cec85d7bea7798e]]",
        "IsRequired": false
      },
      {
        "Name": "inStock",
        "Type": "System.Nullable\u00601[[System.Boolean, System.Private.CoreLib, Version=10.0.0.0, Culture=neutral, PublicKeyToken=7cec85d7bea7798e]]",
        "IsRequired": false
      },
      {
        "Name": "sortBy",
        "Type": "System.String",
        "IsRequired": false
      },
      {
        "Name": "page",
        "Type": "System.Int32",
        "IsRequired": false
      },
      {
        "Name": "pageSize",
        "Type": "System.Int32",
        "IsRequired": false
      }
    ],
    "ReturnTypes": []
  },
  {
    "ContainingType": "ProductCatalog.WebAPI.Controllers.ProductsController",
    "Method": "CreateProductAsync",
    "RelativePath": "api/products",
    "HttpMethod": "POST",
    "IsController": true,
    "Order": 0,
    "Parameters": [
      {
        "Name": "createProductDto",
        "Type": "ProductCatalog.WebAPI.DTOs.Product.CreateProductDto",
        "IsRequired": true
      }
    ],
    "ReturnTypes": []
  },
  {
    "ContainingType": "ProductCatalog.WebAPI.Controllers.ProductsController",
    "Method": "GetProductByIdAsync",
    "RelativePath": "api/products/{id}",
    "HttpMethod": "GET",
    "IsController": true,
    "Order": 0,
    "Parameters": [
      {
        "Name": "id",
        "Type": "System.Int32",
        "IsRequired": true
      }
    ],
    "ReturnTypes": []
  },
  {
    "ContainingType": "ProductCatalog.WebAPI.Controllers.ProductsController",
    "Method": "UpdateProductAsync",
    "RelativePath": "api/products/{id}",
    "HttpMethod": "PUT",
    "IsController": true,
    "Order": 0,
    "Parameters": [
      {
        "Name": "id",
        "Type": "System.Int32",
        "IsRequired": true
      },
      {
        "Name": "updateProductDto",
        "Type": "ProductCatalog.WebAPI.DTOs.Product.UpdateProductDto",
        "IsRequired": true
      }
    ],
    "ReturnTypes": []
  },
  {
    "ContainingType": "ProductCatalog.WebAPI.Controllers.ProductsController",
    "Method": "DeleteProductAsync",
    "RelativePath": "api/products/{id}",
    "HttpMethod": "DELETE",
    "IsController": true,
    "Order": 0,
    "Parameters": [
      {
        "Name": "id",
        "Type": "System.Int32",
        "IsRequired": true
      }
    ],
    "ReturnTypes": []
  }
]